README.txt
setup.cfg
setup.py
docs/HISTORY.txt
raptus/__init__.py
raptus.workflownotification.egg-info/PKG-INFO
raptus.workflownotification.egg-info/SOURCES.txt
raptus.workflownotification.egg-info/dependency_links.txt
raptus.workflownotification.egg-info/entry_points.txt
raptus.workflownotification.egg-info/namespace_packages.txt
raptus.workflownotification.egg-info/not-zip-safe
raptus.workflownotification.egg-info/requires.txt
raptus.workflownotification.egg-info/top_level.txt
raptus/workflownotification/__init__.py
raptus/workflownotification/configure.zcml
raptus/workflownotification/interfaces.py
raptus/workflownotification/overrides.zcml
raptus/workflownotification/sender.py
raptus/workflownotification/utils.py
raptus/workflownotification/Extensions/Install.py
raptus/workflownotification/Extensions/__init__.py
raptus/workflownotification/browser/__init__.py
raptus/workflownotification/browser/configure.zcml
raptus/workflownotification/browser/menu.py
raptus/workflownotification/browser/notification_form.pt
raptus/workflownotification/browser/notification_form.py
raptus/workflownotification/browser/notification_form_standalone.pt
raptus/workflownotification/browser/overrides.zcml
raptus/workflownotification/browser/utils.py
raptus/workflownotification/i18n/raptus.workflownotification-de.po
raptus/workflownotification/i18n/raptus.workflownotification-fr.po
raptus/workflownotification/i18n/raptus.workflownotification.pot
raptus/workflownotification/kss/__init__.py
raptus/workflownotification/kss/configure.zcml
raptus/workflownotification/kss/notification_form.py
raptus/workflownotification/kss/raptus.workflownotification.kss
raptus/workflownotification/profiles/default/cssregistry.xml
raptus/workflownotification/profiles/default/kssregistry.xml
raptus/workflownotification/profiles/default/metadata.xml
raptus/workflownotification/profiles/default/skins.xml
raptus/workflownotification/profiles/uninstall/cssregistry.xml
raptus/workflownotification/profiles/uninstall/kssregistry.xml
raptus/workflownotification/skins/workflownotification/content_status_history.cpt
raptus/workflownotification/skins/workflownotification/content_status_history.cpt.metadata
raptus/workflownotification/skins/workflownotification/content_status_modify.cpy
raptus/workflownotification/skins/workflownotification/content_status_modify.cpy.metadata
