Metadata-Version: 1.0
Name: raptus.workflownotification
Version: 0.3
Summary: Pluggable system to provide a way to send custom notifications to predefined recipients on a workflow transition
Home-page: http://plone.org/products/raptus.workflownotification
Author: Raptus AG
Author-email: skaeser@raptus.com
License: GPL
Keywords: plone workflow notification
Platform: UNKNOWN
Classifier: Programming Language :: Python
Classifier: Topic :: Software Development :: Libraries :: Python Modules
